jaraco/clipboard/Darwin.py
jaraco/clipboard/Linux.py
jaraco/clipboard/Windows.py
jaraco/clipboard/__init__.py
jaraco.clipboard-3.1.0.dist-info/LICENSE
jaraco.clipboard-3.1.0.dist-info/METADATA
jaraco.clipboard-3.1.0.dist-info/WHEEL
jaraco.clipboard-3.1.0.dist-info/top_level.txt
jaraco.clipboard-3.1.0.dist-info/RECORD
